pavlova/__init__.py
pavlova/base.py
pavlova/flask.py
pavlova/parsers.py
pavlova-0.1.3.dist-info/COPYING.LESSER
pavlova-0.1.3.dist-info/LICENSE
pavlova-0.1.3.dist-info/METADATA
pavlova-0.1.3.dist-info/WHEEL
pavlova-0.1.3.dist-info/top_level.txt
pavlova-0.1.3.dist-info/RECORD
