Metadata-Version: 2.1
Name: pavlova
Version: 0.1.3
Summary: Simplified deserialization using dataclasses
Home-page: https://github.com/freelancer/pavlova
Author: Freelancer.com
Author-email: chris@freelancer.com
License: UNKNOWN
Platform: UNKNOWN
Classifier: Development Status :: 3 - Alpha
Classifier: License :: OSI Approved :: GNU Lesser General Public License v3 (LGPLv3)
Classifier: Programming Language :: Python :: 3.7
Requires-Dist: dateparser
